Metadata-Version: 2.4
Name: epb-benchmark
Version: 1.0.1
Summary: Epistemic Pathology Benchmark - The MLPerf of AI Truth Systems
Author-email: Course Correct Labs <hello@coursecorrect.org>
License: MIT
Project-URL: Homepage, https://github.com/Course-Correct-Labs/epb-benchmark
Project-URL: Documentation, https://github.com/Course-Correct-Labs/epb-benchmark/tree/main/docs
Project-URL: Repository, https://github.com/Course-Correct-Labs/epb-benchmark
Project-URL: Issues, https://github.com/Course-Correct-Labs/epb-benchmark/issues
Keywords: ai,benchmark,epistemic,pathology,truthfulness,safety
Classifier: Development Status :: 4 - Beta
Classifier: Intended Audience :: Science/Research
Classifier: License :: OSI Approved :: MIT License
Classifier: Programming Language :: Python :: 3
Classifier: Programming Language :: Python :: 3.9
Classifier: Programming Language :: Python :: 3.10
Classifier: Programming Language :: Python :: 3.11
Classifier: Programming Language :: Python :: 3.12
Classifier: Topic :: Scientific/Engineering :: Artificial Intelligence
Requires-Python: >=3.9
License-File: LICENSE
Requires-Dist: click>=8.0.0
Requires-Dist: pyyaml>=6.0
Requires-Dist: jsonschema>=4.0.0
Requires-Dist: python-Levenshtein>=0.21.0
Requires-Dist: scikit-learn>=1.3.0
Requires-Dist: openai>=1.0.0
Requires-Dist: anthropic>=0.18.0
Requires-Dist: pydantic>=2.0.0
Requires-Dist: tqdm>=4.65.0
Requires-Dist: numpy>=1.24.0
Provides-Extra: leaderboard
Requires-Dist: fastapi>=0.104.0; extra == "leaderboard"
Requires-Dist: uvicorn[standard]>=0.24.0; extra == "leaderboard"
Requires-Dist: sqlalchemy>=2.0.0; extra == "leaderboard"
Requires-Dist: python-multipart>=0.0.6; extra == "leaderboard"
Provides-Extra: dev
Requires-Dist: pytest>=7.4.0; extra == "dev"
Requires-Dist: pytest-cov>=4.1.0; extra == "dev"
Requires-Dist: black>=23.0.0; extra == "dev"
Requires-Dist: ruff>=0.1.0; extra == "dev"
Requires-Dist: mypy>=1.5.0; extra == "dev"
Dynamic: license-file
